splinterglyph/VERSION.py
splinterglyph/__init__.py
splinterglyph/readable_hex.py
splinterglyph/requirements.txt
splinterglyph/shamir.py
splinterglyph/shamir_randomness.py
splinterglyph/shamir_util.py
splinterglyph/splinterglyph_decrypt
splinterglyph/splinterglyph_encrypt
splinterglyph/splinterglyph_tools.py
splinterglyph/words.txt
splinterglyph-0.1.8.data/scripts/splinterglyph_decrypt
splinterglyph-0.1.8.data/scripts/splinterglyph_encrypt
splinterglyph-0.1.8.dist-info/LICENSE
splinterglyph-0.1.8.dist-info/METADATA
splinterglyph-0.1.8.dist-info/WHEEL
splinterglyph-0.1.8.dist-info/top_level.txt
splinterglyph-0.1.8.dist-info/RECORD
