Metadata-Version: 2.1
Name: splinterglyph
Version: 0.1.8
Summary: A tool for encrypting and decrypting files using distributed keys
Home-page: https://github.com/Mirabolic/splinterglyph
Author: Bill Bradley
Classifier: Programming Language :: Python :: 3
Classifier: License :: OSI Approved :: MIT License
Classifier: Operating System :: OS Independent
License-File: LICENSE
Requires-Dist: pycryptodome (>=3.18.0)
